server/__init__.py
server/server.py
server/common/__init__.py
server/common/decorator.py
server/common/descryptors.py
server/common/errors.py
server/common/metaclasses.py
server/common/utils.py
server/common/variables.py
server/logs/__init__.py
server/logs/client_log_config.py
server/logs/server_log_config.py
server/server_data/__init__.py
server/server_data/add_user.py
server/server_data/config_window.py
server/server_data/core.py
server/server_data/database.py
server/server_data/main_window.py
server/server_data/remove_user.py
server/server_data/stat_window.py
server/unit_test/__init__.py
server_for_message_march_26-0.7.0.dist-info/METADATA
server_for_message_march_26-0.7.0.dist-info/WHEEL
server_for_message_march_26-0.7.0.dist-info/top_level.txt
server_for_message_march_26-0.7.0.dist-info/RECORD
