Metadata-Version: 2.1
Name: server-for-message-march-26
Version: 0.7.0
Summary: mess_server
Home-page: UNKNOWN
Author: Ivan Necris45 Sizikov
Author-email: Necris01@mail.ru
License: UNKNOWN
Platform: UNKNOWN
Requires-Dist: PyQt5
Requires-Dist: sqlalchemy
Requires-Dist: pycryptodome
Requires-Dist: pycryptodomex
